stock_data_mcp/__init__.py
stock_data_mcp/__main__.py
stock_data_mcp/_version.py
stock_data_mcp/cache.py
stock_data_mcp/data_provider/__init__.py
stock_data_mcp/data_provider/akshare_fetcher.py
stock_data_mcp/data_provider/alphavantage_fetcher.py
stock_data_mcp/data_provider/baostock_fetcher.py
stock_data_mcp/data_provider/base.py
stock_data_mcp/data_provider/efinance_fetcher.py
stock_data_mcp/data_provider/tushare_fetcher.py
stock_data_mcp/data_provider/types.py
stock_data_mcp/data_provider/yfinance_fetcher.py
stock_data_mcp-0.2.1.dist-info/METADATA
stock_data_mcp-0.2.1.dist-info/WHEEL
stock_data_mcp-0.2.1.dist-info/entry_points.txt
stock_data_mcp-0.2.1.dist-info/licenses/LICENSE
stock_data_mcp-0.2.1.dist-info/RECORD
