Metadata-Version: 2.4
Name: stock-data-mcp
Version: 0.2.1
Summary: MCP Server for stock and crypto with multi-source failover
Project-URL: Homepage, https://github.com/stockmcp/stock-data-mcp
Project-URL: Repository, https://github.com/stockmcp/stock-data-mcp.git
License: MIT
License-File: LICENSE
Keywords: akshare,efinance,llm,mcp,multi-source,stock,trading,tushare
Requires-Python: >=3.10
Requires-Dist: akshare>=1.17.0
Requires-Dist: baostock>=0.8.8
Requires-Dist: cachetools>=6.2.0
Requires-Dist: diskcache>=5.6.0
Requires-Dist: efinance>=0.5.0
Requires-Dist: fastmcp>=2.0.0
Requires-Dist: tenacity>=8.0.0
Requires-Dist: tushare>=1.4.0
Requires-Dist: yfinance>=0.2.0
